MANIFEST.in
setup.py
docs/HISTORY.txt
src/zeam/__init__.py
src/zeam.utils.batch.egg-info/PKG-INFO
src/zeam.utils.batch.egg-info/SOURCES.txt
src/zeam.utils.batch.egg-info/dependency_links.txt
src/zeam.utils.batch.egg-info/namespace_packages.txt
src/zeam.utils.batch.egg-info/not-zip-safe
src/zeam.utils.batch.egg-info/requires.txt
src/zeam.utils.batch.egg-info/top_level.txt
src/zeam/utils/__init__.py
src/zeam/utils/batch/README.txt
src/zeam/utils/batch/__init__.py
src/zeam/utils/batch/batch.py
src/zeam/utils/batch/batch.txt
src/zeam/utils/batch/configure.zcml
src/zeam/utils/batch/ftesting.zcml
src/zeam/utils/batch/interfaces.py
src/zeam/utils/batch/tests.py
src/zeam/utils/batch/views.py
src/zeam/utils/batch/views.txt
src/zeam/utils/batch/alphabetical/__init__.py
src/zeam/utils/batch/alphabetical/batch.py
src/zeam/utils/batch/alphabetical/batch.txt
src/zeam/utils/batch/alphabetical/tests.py
src/zeam/utils/batch/alphabetical/views.py
src/zeam/utils/batch/alphabetical/views_templates/batchpages.pt
src/zeam/utils/batch/date/__init__.py
src/zeam/utils/batch/date/batch.py
src/zeam/utils/batch/date/batch.txt
src/zeam/utils/batch/date/tests.py
src/zeam/utils/batch/date/views.py
src/zeam/utils/batch/date/views_templates/batchpages.pt
src/zeam/utils/batch/i18n/zeam.pot
src/zeam/utils/batch/i18n/en/LC_MESSAGES/zeam.mo
src/zeam/utils/batch/i18n/en/LC_MESSAGES/zeam.po
src/zeam/utils/batch/i18n/fr/LC_MESSAGES/zeam.mo
src/zeam/utils/batch/i18n/fr/LC_MESSAGES/zeam.po
src/zeam/utils/batch/i18n/nl/LC_MESSAGES/zeam.mo
src/zeam/utils/batch/i18n/nl/LC_MESSAGES/zeam.po
src/zeam/utils/batch/views_templates/batchpages.pt