Metadata-Version: 1.0
Name: zeam.utils.batch
Version: 1.1
Summary: Generic Batch support for Zope
Home-page: http://github.com/thefunny42/Zeam-Utils-Batch
Author: Sylvain Viollon
Author-email: thefunny@gmail.com
License: BSD
Keywords: batch zope
Platform: UNKNOWN
Classifier: Framework :: Zope2
Classifier: Framework :: Zope3
Classifier: Programming Language :: Python
Classifier: Topic :: Software Development :: Libraries :: Python Modules
Classifier: License :: OSI Approved :: BSD License
